aptos_indexer_protos/__init__.py
aptos_indexer_protos/aptos/bigquery_schema/v1/transaction_pb2.py
aptos_indexer_protos/aptos/bigquery_schema/v1/transaction_pb2.pyi
aptos_indexer_protos/aptos/bigquery_schema/v1/transaction_pb2_grpc.py
aptos_indexer_protos/aptos/indexer/v1/raw_data_pb2.py
aptos_indexer_protos/aptos/indexer/v1/raw_data_pb2.pyi
aptos_indexer_protos/aptos/indexer/v1/raw_data_pb2_grpc.py
aptos_indexer_protos/aptos/internal/fullnode/v1/fullnode_data_pb2.py
aptos_indexer_protos/aptos/internal/fullnode/v1/fullnode_data_pb2.pyi
aptos_indexer_protos/aptos/internal/fullnode/v1/fullnode_data_pb2_grpc.py
aptos_indexer_protos/aptos/transaction/v1/transaction_pb2.py
aptos_indexer_protos/aptos/transaction/v1/transaction_pb2.pyi
aptos_indexer_protos/aptos/transaction/v1/transaction_pb2_grpc.py
aptos_indexer_protos/aptos/util/timestamp/timestamp_pb2.py
aptos_indexer_protos/aptos/util/timestamp/timestamp_pb2.pyi
aptos_indexer_protos/aptos/util/timestamp/timestamp_pb2_grpc.py
aptos_indexer_protos-0.1.1.dist-info/METADATA
aptos_indexer_protos-0.1.1.dist-info/WHEEL
aptos_indexer_protos-0.1.1.dist-info/RECORD
